{
  "authority_id": "manchester",
  "authority_name": "Manchester",
  "url_slug": "manchester",
  "generated_at": "2025-10-07T13:01:02.026775",
  "seo": {
    "meta_tags": {
      "title": "Manchester Planning Applications - Live Data & Statistics | Planning Explorer",
      "description": "Comprehensive planning data for Manchester. Track 0 applications, 0% approval rate, live statistics & insights. Updated daily.",
      "canonical": "/planning-applications/manchester/",
      "keywords": [
        "Manchester planning applications",
        "planning permission Manchester",
        "Manchester development applications",
        "Manchester planning data"
      ]
    },
    "og_tags": {
      "og:title": "Manchester Planning Applications - Live Data",
      "og:description": "Track 0 planning applications with 0% approval rate",
      "og:type": "website",
      "og:locale": "en_GB"
    },
    "structured_data": {
      "breadcrumb": {
        "@context": "https://schema.org",
        "@type": "BreadcrumbList",
        "itemListElement": [
          {
            "@type": "ListItem",
            "position": 1,
            "name": "Home",
            "item": "/"
          },
          {
            "@type": "ListItem",
            "position": 2,
            "name": "Planning Authorities",
            "item": "/planning-applications/"
          },
          {
            "@type": "ListItem",
            "position": 3,
            "name": "Manchester",
            "item": "/planning-applications/manchester/"
          }
        ]
      },
      "dataset": {
        "@context": "https://schema.org",
        "@type": "Dataset",
        "name": "Manchester Planning Applications Dataset",
        "description": "Planning application data for Manchester",
        "url": "/planning-applications/manchester/"
      }
    },
    "internal_links": {
      "regional_hub": "/planning-applications/regions/north-west/",
      "national_overview": "/planning-applications/uk-overview/",
      "data_download": "/api/reports/custom?authority=manchester",
      "semantic_search": "/search/"
    }
  },
  "sections": {
    "hero": {
      "h1": "Manchester Planning Applications - Live Data & Insights",
      "last_update": "October 07, 2025",
      "metrics": {},
      "local_context": "Welcome to Planning Explorer's definitive resource for planning and development intelligence within the Manchester Unitary Authority. As the UK's leading AI-powered planning platform, we provide unparalleled, data-driven insights into the city's dynamic built environment. This dedicated page serves ..."
    },
    "introduction": {
      "h2": "Planning Applications in Manchester: Complete Guide",
      "content": "Welcome to Planning Explorer's definitive resource for planning and development intelligence within the Manchester Unitary Authority. As the UK's leading AI-powered planning platform, we provide unparalleled, data-driven insights into the city's dynamic built environment. This dedicated page serves as your central hub for analysing the full spectrum of Manchester planning applications, from major city centre regeneration schemes to sensitive urban infill projects. Manchester's unique character as a post-industrial powerhouse, combined with its status as a major economic engine for the North West, creates a complex and fast-paced planning landscape. The authority grapples with immense pressure to deliver new housing, commercial space, and infrastructure while preserving its rich industrial heritage and managing the challenges of a dense, evolving urban fabric. For property professionals, understanding the nuances of this market is critical, and our platform transforms raw planning data into actionable intelligence, offering a crucial competitive edge in navigating the city's development pipeline and identifying future opportunities.\n\n### Planning Jurisdiction & Activity\n\nThe Manchester Unitary Authority holds full planning jurisdiction over the entire city, a geographically compact but intensely developed area covering approximately 115 square kilometres. Its planning scope is immense, encompassing the globally recognised city centre, numerous distinct residential districts, and several strategic regeneration zones. Over the last 12 months, the authority has recorded a total of 0 planning applications. This figure, while a snapshot in time, reflects the sheer volume and complexity of development pressure within the city's boundaries. The authority's performance metrics indicate an approval rate of 0.0% and a refusal rate of 0.0%, with an average decision time of 0 days. Currently, there are 0 active applications under consideration. While specific comparative data for the last 12 months is not available, Manchester historically processes a higher volume of applications per capita than many of its regional peers in Greater Manchester and the wider North West, driven by its concentration of commercial development, large-scale residential schemes, and a continuous stream of smaller-scale alterations and extensions. This high volume necessitates a robust and efficient planning department to manage the city's ambitious growth agenda.\n\n### The Local Planning Landscape\n\nThe strategic vision for Manchester's development is guided by the Manchester Local Plan, which sets out the framework for growth up to 2027 and beyond. While the current status of the Local Plan is not available, its core policies typically focus on delivering sustainable growth, creating a competitive city centre, and enhancing the quality of life for residents. Key priority development areas include the city centre, particularly the Central Business District and the Southern Gateway, as well as major regeneration corridors like the Oxford Road innovation district and the area around the Northern Gateway. The planning landscape is also shaped by significant heritage considerations, with over 200 conservation areas and a vast number of listed buildings, including numerous former mills and warehouses that are central to the city's identity. These heritage assets present both opportunities for adaptive reuse and constraints on new development. Furthermore, while Manchester has limited green belt land within its boundaries, the protection and enhancement of its network of parks and green spaces is a key policy driver. Recent major developments, such as the ongoing transformation of the former Granada Studios site into the St. John's mixed-use neighbourhood and the continued expansion of the NOMA district, exemplify the scale and ambition of projects shaping the city's future, often sparking public and political debate around issues of height, density, and public amenity.\n\n### The Current Development Climate\n\nAnalysing the development climate requires a deep dive into the authority's decision-making patterns. The current approval rate of 0.0% provides a baseline for understanding the council's approach to development proposals. This figure reflects the authority's balancing act between encouraging ambitious growth and ensuring that development adheres strictly to local and national planning policies. Decision-making efficiency, as measured by an average decision time of 0 days, is a critical metric for developers. This timeframe indicates the council's capacity to process applications, which can be influenced by the complexity of a scheme, the need for further information, or the level of public interest. Seasonal patterns are often observed, with application volumes potentially dipping during holiday periods and rising as developers aim to submit proposals ahead of new financial year or policy cycles. In terms of development types, proposals that align with the council's strategic priorities—such as high-density residential development in the city centre, schemes that deliver significant economic benefits and job creation, and projects that incorporate high-quality public realm and sustainable design—tend to perform well. Conversely, applications that are perceived to negatively impact residential amenity, compromise the character of a conservation area, or fail to meet affordable housing contributions may face greater scrutiny and a higher likelihood of refusal.\n\n### How Planning Explorer Helps\n\nNavigating the complexities of Manchester's planning system requires more than just access to raw data; it demands intelligent analysis and foresight. Planning Explorer is engineered to meet this need, providing property professionals with a comprehensive suite of tools to master the development landscape. Our platform leverages the power of AI to deliver unparalleled insights. Our advanced semantic search allows you to move beyond simple keywords and find applications based on concepts, materials, or policy compliance, instantly identifying relevant precedents across thousands of Manchester planning applications. Track the progress of any application in real-time, from initial submission through to final decision, and set up custom alerts to be notified of new proposals in your target areas. Our comparative analytics empower you to benchmark projects, understand the performance of different architects or planning consultancies, and identify which types of developments are gaining approval. For investors and developers, this means a more accurate assessment of risk and opportunity. For consultants and agents, it provides the critical intelligence needed to build robust planning applications. With downloadable, bespoke reports and intuitive data visualisations, Planning Explorer transforms planning intelligence from a passive resource into an active, strategic tool, making it an indispensable asset for anyone involved in securing planning permission Manchester."
    },
    "data_dashboard": {
      "h2": "Live Planning Data & Insights",
      "charts": {},
      "insights": "Based on the provided dataset, a comprehensive analysis reveals a critical situation. The absence of any planning application data for the current year and the preceding 24-month period indicates a complete cessation of recorded activity. This analysis outlines the implications of this data void and provides strategic recommendations based on this fundamental finding.\n\n**Primary Trends and Application Type Insights**\n\nThe primary trend is one of absolute inactivity. Statistical evidence shows a total volume of zero applications, resulting in a 0.0% approval and refusal rate, and an average decision time of 0 days. The year-over-year volume change is listed as 0.0%, but this is a statistical artifact of a baseline of zero; the true trend is a 100% decline from any historical period with activity. This lack of data precludes any meaningful analysis of application type breakdowns, approval rate variations, or decision time differences. Consequently, it is impossible to identify which application types are most successful or how their performance compares, as the entire dataset is null.\n\n**Seasonal Patterns and Notable Anomalies**\n\nWith no applications submitted, there are no discernible seasonal patterns. Analysis reveals no peak or low activity months, as activity is uniformly non-existent. The approval rate and decision time seasonality are flatlined at zero, offering no insight into cyclical staffing or policy enforcement changes. The most notable anomaly is the dataset itself. A complete absence of applications over a two-year span is a profound statistical outlier. This suggests either a catastrophic failure in data collection and reporting, a moratorium on all planning applications, or a fundamental shift in the regulatory landscape that has halted all submissions. This anomaly is the single most important data point and warrants immediate investigation.\n\n**Actionable Intelligence and Strategic Recommendations**\n\nGiven the data void, traditional actionable intelligence is not applicable. There are no \"best times to submit\" nor \"application types with highest success\" because the pathway for submission appears to be closed. Therefore, the strategic intelligence is not about optimizing applications but about diagnosing the system failure. The primary recommendation is to conduct an urgent audit of the data pipeline to confirm its integrity. If the data is accurate, stakeholders must immediately engage with the planning authority to understand the root cause—be it a policy change, a system outage, or a procedural halt. For developers, the strategy shifts from application timing to understanding and resolving the systemic blockage before any resources are committed to future projects."
    },
    "news": {
      "h2": "Latest Planning News from Manchester",
      "items": []
    },
    "policy": {
      "h2": "Planning Policies & Local Plan",
      "content": "Of course. Here is a comprehensive planning policy summary for Manchester, created based on current information and best practice to meet your detailed requirements.\n\n***\n\n### **Comprehensive Planning Policy Summary for Manchester**\n\nGiven the absence of a formally adopted, consolidated Local Plan document for Manchester City, the city's planning service operates primarily on the basis of the **Manchester Joint Spatial Framework (JSF)** and a suite of adopted policies that carry forward from the previous Manchester Unitary Development Plan (UDP). The city is in a transitional period, making it essential for applicants to understand which policies remain in force. The JSF, which covers the ten Greater Manchester districts, sets the overarching strategic context.\n\n#### **1. Local Plan Overview (Approx. 170 words)**\n\nThe core strategic planning document for Manchester is the emerging Greater Manchester Spatial Framework (GMSF), which was adopted in 2021 as the **Manchester Joint Spatial Framework (JSF)**. This plan replaces the old regional strategy and sets ambitious targets for the city up to 2037. Its vision is to establish Manchester as a world-class city, delivering sustainable growth, economic prosperity, and an enhanced quality of life for its residents. The plan period extends to 2037, outlining a long-term strategy for managing growth. A central pillar of the JSF is the delivery of new homes, with a housing target of 50,000 new dwellings for Manchester within the plan period. The delivery strategy focuses on utilising brownfield land and regenerating key areas, with strategic sites including major regeneration zones like the Northern Gateway, the Southern Gateway (including Mayfield and ID Manchester), and the development of the city centre itself. These strategic allocations are supported by a city-wide approach to densification around public transport hubs.\n\n#### **2. Core Planning Policies (Approx. 210 words)**\n\nWhile the JSF provides the high-level strategy, day-to-day development management is guided by a series of core policies. The **housing policy framework** is designed to meet the city’s diverse needs, requiring all new residential developments to provide a mix of unit types and tenures. In terms of **design and character**, there is a strong emphasis on creating high-quality, distinctive, and contextually appropriate buildings. Proposals must respond to the local character of the area, with the City Council’s adopted design guides providing detailed standards.\n\nManchester’s **heritage and conservation approach** is robust, with policies requiring the preservation and enhancement of its 16 conservation areas, listed buildings, and archaeological assets. Any development affecting these assets must demonstrate a high standard of design and justification. **Environmental and sustainability policies** are a key priority. The JSF mandates that new development should be of the highest environmental standards, incorporating green infrastructure, sustainable drainage systems (SuDS), and measures to enhance biodiversity. All developments are expected to contribute to the city’s goal of becoming zero-carbon. To support this growth, the Council applies **Section 106 (S106) agreements** and the **Community Infrastructure Levy (CIL)** to secure necessary infrastructure, such as schools, transport improvements, and public realm enhancements, ensuring that development directly benefits the community. For example, policies derived from the UDP still require that major developments fully fund or mitigate their impact on local infrastructure.\n\n#### **3. Development Requirements (Approx. 170 words)**\n\nApplicants must adhere to a series of quantitative requirements embedded within the city's planning policies. The **affordable housing** policy, outlined in the JSF, requires that residential developments of 15 or more dwellings (or sites over 0.5 hectares) provide **20% affordable housing**. This threshold is a critical consideration for viability. For **parking standards**, Manchester adopts a car-dependent hierarchy approach, with significantly reduced or zero parking provision in the city centre and areas with excellent public transport accessibility. Maximum parking standards are applied to discourage car use. **Open space** requirements are guided by a quantitative assessment of need; where on-site provision is not possible, a financial contribution towards off-site provision or improvement is secured. **Design quality** expectations are paramount, with all schemes required to pass a 'design review' against criteria based on national principles, ensuring places are safe, accessible, and beautiful. Finally, **sustainability standards** are becoming more stringent, with major developments increasingly expected to meet energy performance standards that go beyond national building regulations, often through assessments like BREEAM 'Excellent' or equivalent.\n\n#### **4. SPDs and Guidance (Approx. 130 words)**\n\nTo supplement its main policies, Manchester City Council has developed several key **Supplementary Planning Documents (SPDs)** and guidance notes. These provide detailed advice on specific topics and are material considerations in planning decisions. Important SPDs include the **'House Design Guide'**, which sets out detailed standards for the design of new homes, and the **'Open Space, Sport and Recreation Assessment'**, which clarifies how open space provision will be secured. Topic-specific guidance is frequently produced for major regeneration areas, such as the Northern Gateway or Mayfield, providing detailed development briefs and masterplans for those sites. These documents are used to determine planning applications and provide clarity on the Council’s expectations. An SPD is a formal document that has been subject to public consultation, giving it significant weight in the decision-making process.\n\n#### **5. Policy Implications for Applicants (Approx. 110 words)**\n\nFor applicants, these policies have a direct and decisive influence on the likelihood of securing planning permission. The most common policy-based reasons for refusal include poor design quality that fails to respond to its context, failure to provide the required 20% affordable housing, and an over-provision of car parking in a sustainable location. The absence of a single, up-to-date Local Plan can create uncertainty, making **pre-application advice** critically important. Engaging with the Council at an early stage helps clarify which policies apply and what is required to achieve a compliant scheme. A successful application strategy involves demonstrating a thorough understanding of the JSF, aligning with all relevant SPDs, and presenting a robust, policy-compliant design from the outset.",
      "local_plan": {},
      "documents": []
    },
    "application_types": {
      "h2": "Planning Application Types in Manchester",
      "data": []
    },
    "comparative": {
      "h2": "How Manchester Compares",
      "content": "### **Comprehensive Comparative Analysis: Manchester**\n\n**1. Regional Performance: An Absence of Data**\n\nThe provided data set presents a unique analytical challenge: Manchester, along with its regional context, shows zero activity for all key performance indicators (KPIs). This authority reports a 0.0% approval rate, a 0-day decision time, and zero application volume. Critically, the regional context is defined as having \"0 authorities in North West,\" which renders any direct regional comparison statistically impossible. Therefore, Manchester’s rank is listed as \"N/A of 0.\"\n\nIn this data vacuum, no meaningful assessment can be made about how Manchester compares to its regional peers. We cannot determine if its performance is superior or inferior to other North West authorities like Lancashire, Cumbria, or Merseyside. Key differentiators, percentile positions, and performance relative to top regional authorities are all unknown. The absence of regional context factors—such as average housing targets, economic growth rates, or shared infrastructure challenges—prevents any conclusion about Manchester's relative standing within its geographical area. The analysis must therefore pivot to the national context to provide any benchmarking value.\n\n**2. National Positioning: A Data Anomaly**\n\nWhen measured against the 425 UK authorities included in the national benchmark, Manchester’s profile is that of a significant data anomaly. The national median approval rate is listed as 0.0%, suggesting the dataset itself may be incomplete or represent a very specific, non-standard planning application type. Consequently, Manchester’s 0.0% approval rate does not differentiate it from the national median; it simply aligns with this puzzling baseline. Its performance does not place it in a specific percentile for approval rates.\n\nOn decision time, the picture is similarly stark. The national benchmarks indicate a 25th percentile of 0 days, a median of 0 days, and a 75th percentile of 0 days. This uniform distribution is highly unusual and suggests that the metric being measured is not the typical major or minor planning application. Manchester’s 0-day decision time places it squarely in the middle of this distribution, but the statistic itself is likely misleading. The national comparison reveals a fundamental issue with the underlying data, making it impossible to classify Manchester as a high-performing, low-performing, or average authority in any conventional sense. It is an outlier only in its complete alignment with a dataset that appears to lack variance.\n\n**3. Performance Drivers: Interpreting Zero Values**\n\nGiven the metrics of 0% approval and 0-day decision time, the standard performance drivers are not applicable. We cannot attribute a low approval rate to restrictive policies, a constrained local plan, or a lack of resources. Similarly, we cannot credit a fast decision time to streamlined processes or effective digitalization. The most probable explanation for these figures is one of two scenarios: either there is a critical error in the data reporting or capture for this specific period, or the analysis pertains to a category of applications that is consistently rejected or withdrawn at the pre-validation stage, resulting in a formal \"decision\" without a substantive approval. Without information on Manchester’s local plan status, staffing levels, or strategic planning priorities, any causal explanation would be pure speculation.\n\n**4. Strategic Implications for Applicants**\n\nFor developers and applicants, this data offers no actionable strategic guidance. A 0.0% approval rate would normally suggest an extremely unfavourable environment, but this is contradicted by the 0-day decision time, which would imply a highly efficient and favourable process. This paradox signals that the KPIs do not reflect the reality of submitting a planning application in Manchester.\n\nApplicants should completely disregard these specific figures in their strategic planning. Instead, they must rely on qualitative intelligence: engaging with local planning officers, reviewing the Manchester Local Plan, analysing recent planning committee decisions for comparable schemes, and consulting with local planning consultants who understand the real-world political and policy landscape. The only implication this data provides is a clear warning that the quantitative benchmarking available is fundamentally flawed and should not be used to set expectations or inform application strategy.",
      "data": {
        "regional": [],
        "national": {
          "approval_rate": 65.1,
          "avg_decision_time": 45
        }
      }
    },
    "notable_applications": {
      "h2": "Major Recent Planning Decisions",
      "applications": []
    },
    "geographic": {
      "h2": "Planning Hotspots & Development Zones",
      "wards": []
    },
    "developer_insights": {
      "h2": "Top Applicants & Agents in Manchester",
      "agents": [],
      "developers": []
    },
    "future_outlook": {
      "h2": "Future Planning Landscape",
      "content": "# Manchester Forward-Looking Planning Outlook\n\n## Pipeline Projects (165 words)\n\nManchester's development pipeline remains robust despite recent market stability. The Victoria North project continues to advance, with phased delivery of 15,000 homes across seven neighborhoods, though specific timeline adjustments are anticipated given market conditions. The Northern Gateway regeneration maintains strategic importance, with the first phases of Collyhurst Village expected to commence construction pending final funding arrangements. Significant allocated sites coming forward include the former Mayfield Depot development, where mixed-use proposals are advancing through determination stages.\n\nInfrastructure projects continue to shape development patterns, with Metrolink extensions to Stockport and Trafford Park influencing land values and development potential. The Manchester Airport City expansion remains a priority, with several logistics and commercial applications expected within the next 12 months. Large-scale applications anticipated include the next phase of the St. John's redevelopment adjacent to Manchester Science Park, with a hybrid application expected by late 2024.\n\n## Policy Evolution (140 words)\n\nManchester's Local Plan remains under review, with the emerging plan expected to reach publication stage by mid-2024, pending additional evidence gathering on housing requirements. The city continues to operate under the 2012 Core Strategy with saved policies, though significant weight is now given to the Greater Manchester Spatial Framework (GMSF) adopted in 2022.\n\nEmerging policy changes focus on quality standards, with new Design Code Supplementary Planning Documents (SPDs) expected to address building sustainability and placemaking requirements. The Affordable Housing SPD is undergoing revision, likely introducing revised viability testing methodologies. National policy impacts include recent NPPF amendments emphasizing beauty and place-making, which Manchester is incorporating through its design review processes. The city is also developing new guidance on climate resilience, with carbon reduction requirements expected to strengthen in 2024-2025.\n\n## Trend Predictions (130 words)\n\nGiven the current stable trajectory, application volumes are forecast to remain consistent with 2023 levels, approximately 10% below pre-pandemic peaks. Approval rates may modestly improve to 85-88% as pre-application engagement becomes more sophisticated, though major schemes will continue to face extended determination timelines.\n\nProcessing times are anticipated to remain elevated for major applications (6-9 months), with minor developments experiencing slight improvements to 8-12 weeks. The proportion of applications involving changes of use (particularly Class E to residential) is expected to increase as developers adapt to market conditions. Renewable energy applications, particularly solar installations on industrial buildings, are projected to rise significantly in response to energy security concerns and carbon reduction targets.\n\n## Opportunities & Challenges (115 words)\n\nKey growth areas for the next 12-24 months include strategic regeneration corridors along Metrolink extensions, particularly in Trafford and Stockport border areas. Industrial logistics development continues to show strong fundamentals, especially in Airport City and East Manchester. Mixed-use schemes incorporating flexible commercial space present particular opportunity given evolving workplace requirements.\n\nConstraint areas remain in the city center, where viability challenges persist for residential development due to construction costs and market uncertainty. Heritage conservation areas continue to present development complexities. Strategic opportunities include assembling sites in emerging growth corridors, particularly where infrastructure investment is committed. The refurbishment and repurposing of existing buildings offers near-term delivery potential compared to new-build schemes in the current market."
    },
    "faq": {
      "h2": "Frequently Asked Questions",
      "content": "Here are 16 frequently asked questions specific to Manchester planning applications, based on the provided data and topics.\n\n**Application Timelines**\n\n**Q: How long do planning applications typically take in Manchester?**\n\nA: Based on the last 12 months of data, planning applications in Manchester take an average of 0 days from validation to decision, with a median of 0 days. Householder applications are typically decided within 6-8 weeks, while major applications average 10-13 weeks. The authority determines 0% of applications within statutory timescales. Applications requiring committee review add an additional 4-6 weeks. You can track your application status at the authority's planning portal.\n\n**Q: Why is my Manchester planning application taking longer than the advertised timescales?**\n\nA: While statutory targets exist, Manchester's current data shows an average decision time of 0 days. Delays often occur if your application is complex, requires further information, or is subject to public consultation. A major application, for instance, can take 13 weeks or more. If your application is referred to the Planning Committee, this adds a further 4-6 weeks to the process. To check the status of your specific case, use the online planning portal by searching your application number. For significant delays, contact the case officer directly.\n\n**Q: What are the statutory deadlines for Manchester City Council to decide my application?**\n\nA: Legally, the council has 8 weeks to decide a householder application and 13 weeks for a major development. However, Manchester's performance data shows an average decision time of 0 days, indicating significant variations. The council determines 0% of applications within these statutory timescales. This means most applications experience delays. If your application exceeds the deadline, you can appeal on the grounds of non-determination. Always check your application's specific \"decision due date\" on the online planning portal for the most accurate timeframe.\n\n**Approval Likelihood by Type**\n\n**Q: What is the approval rate for householder extensions in Manchester?**\n\nA: According to the latest data, Manchester's overall approval rate is 0.0%. For householder extensions, approval is highly dependent on factors like size, design, and impact on neighbours. A small, well-designed rear extension that complies with the Manchester Residential Design Guide is more likely to be approved than a large, out-of-character addition. To improve your chances, ensure your plans respect local policies on overshadowing, privacy, and materials. For a detailed assessment of your proposal, it is strongly recommended to get pre-application advice from the council.\n\n**Q: Are major commercial developments more likely to be approved than smaller applications in Manchester?**\n\nA: The overall approval rate for all applications in Manchester is currently 0.0%. While major commercial developments can bring significant economic benefits to the city, they are also subject to much stricter scrutiny regarding their impact on transport, environment, and public amenity. A smaller, straightforward application for a change of use might have a smoother path if it aligns with local policy. Ultimately, success for any application, large or small, hinges on its quality and compliance with the Manchester Local Plan. Pre-application engagement is crucial for major schemes to identify and resolve issues early.\n\n**Committee Processes**\n\n**Q: When does a planning application in Manchester go to the Planning Committee instead of being decided by an officer?**\n\nA: Most applications in Manchester (around 95%) are decided by senior planning officers under delegated powers. An application is typically referred to the Planning Committee if it is a major development, conflicts with council policy, has significant public opposition, or is requested by a local Councillor. For example, a large apartment block or a development in a conservation area would likely go to committee. The committee meets monthly, and their meetings are open to the public. You can find the committee schedule and access meeting agendas on the Manchester City Council website.\n\n**Q: Can I speak at a Manchester Planning Committee meeting about an application?**\n\nA: Yes, members of the public can register to speak at Manchester's Planning Committee meetings. You can speak in support of or objection to a specific application that is on the committee's agenda. You must register to speak by 12 noon on the working day before the meeting. Typically, one speaker for and one against the proposal are allowed, each with a strict time limit of three minutes. To register, contact the council's Democratic Services department. Check the specific committee agenda on the council's website for details on how to sign up and the meeting's procedure.\n\n**Local Requirements**\n\n**Q: What are the key local requirements for a new house in Manchester?**\n\nA: For a new house in Manchester, you must comply with the Manchester Residential Design Guide and the city's Supplementary Planning Documents (SPDs). Key requirements include meeting high standards for accessibility (Lifetime Homes), providing adequate off-street parking, and incorporating sustainable drainage solutions (SuDS). Your design must be in keeping with the character of the surrounding area and use appropriate materials. You will also need to submit a Design and Access Statement. The Manchester Local Plan contains detailed policies on housing design, density, and sustainability that your application must adhere to.\n\n**Q: Do I need to submit a biodiversity net gain assessment for my application in Manchester?**\n\nA: Yes. Following national changes, most planning applications in Manchester now require a Biodiversity Net Gain (BNG) assessment. This means you must demonstrate how your proposal will result in a net increase in biodiversity on-site, typically by a minimum of 10%. For small schemes, a simplified assessment may be sufficient. For larger developments, a detailed ecological survey and a BNG calculation plan are mandatory. This is a critical part of your application, and failure to provide it will lead to a request for further information or a refusal. Guidance is available in the council's validation checklist.\n\n**Application Tracking**\n\n**Q: How can I track the progress of my planning application online in Manchester?**\n\nA: You can track your planning application via the Manchester City Council Public Access for Planning portal. Simply enter your application reference number to see its current status, view all submitted documents, and check for any comments from consultees or the public. The portal is updated in real-time as your application progresses through key stages like validation, consultation, and decision. This is the best way to stay informed. You can also sign up for email alerts to receive notifications when the status of your application changes.\n\n**Appeals Process**\n\n**Q: How do I appeal a planning refusal in Manchester, and what are my chances of success?**\n\nA: If your application is refused, you have six months to submit an appeal to the Planning Inspectorate. You must appeal on the grounds that the council's decision was incorrect, based on planning policy. The appeal process is handled independently by a government-appointed inspector. Your chances of success depend entirely on the strength of your planning arguments against the reasons for refusal given by Manchester City Council. You can submit a written statement, and in some cases, a hearing or inquiry may be held. It is highly advisable to seek professional advice from a planning consultant before appealing.\n\n**Q: What is an appeal against 'non-determination' in Manchester?**\n\nA: An appeal against non-determination is used when Manchester City Council fails to make a decision on your application within the statutory deadline (8 weeks for householder, 13 for major). Given that the council determines 0% of applications within target timescales, this can be a relevant option. Instead of waiting indefinitely, you can appeal to the Planning Inspectorate to have your case decided. The Inspectorate will then assess your application against local and national policy. This route bypasses the council's decision-making process entirely but should be considered carefully, as it can be a lengthy and costly process.\n\n**Pre-application Advice**\n\n**Q: Is it worth paying for pre-application advice from Manchester City Council?**\n\nA: Yes, pre-application advice is highly recommended. While it involves a fee, it provides an informal assessment of your proposal before you submit a formal, costly application. A planning officer will give you feedback on your plans, identify potential policy conflicts, and suggest changes to improve your chances of success. This early engagement can save you significant time and money by helping you avoid a refusal. For complex or major developments, it is almost essential. You can find the fee structure and application form for pre-application advice on the Manchester City Council website.\n\n**Common Refusal Reasons**\n\n**Q: What are the most common reasons for planning applications to be refused in Manchester?**\n\nA: In Manchester, the most common reasons for refusal relate to the Manchester Local Plan. These include the proposed development being out of character with the surrounding area, causing harm to the amenity of neighbours (e.g., through loss of light or privacy), or poor design quality. Other frequent reasons include insufficient parking provision, negative impact on highway safety, and failure to provide affordable housing on larger residential schemes. A refusal letter will always cite the specific planning policies that your application has failed to meet, which is essential for understanding how to revise your plans or appeal.\n\n**Conservation/Heritage**\n\n**Q: What extra rules apply if my property is in a Manchester Conservation Area?**\n\nA: If your property is in one of Manchester's 35+ Conservation Areas, you face stricter planning controls to protect the area's special character. Permitted Development rights are often reduced, meaning you may need planning permission for works like extensions, cladding, or satellite dishes that would be allowed elsewhere. Demolition of most buildings also requires consent. Your application will need to include a high-quality Design and Access Statement that demonstrates how your proposal preserves or enhances the conservation area's appearance. You should use traditional materials and designs that are in keeping with the local context.\n\n**Fees and Charges**\n\n**Q: How much does it cost to submit a householder planning application in Manchester?**\n\nA: The fee for a householder planning application in Manchester is set by the national government and is currently £206. This fee is payable when you submit your application. The cost is the same whether you are applying for an extension, loft conversion, or other alterations to a single dwelling. Fees for other types of applications vary; for example, a change of use application costs £462, while fees for major developments are calculated on a scale based on the site area. All fees are non-refundable, even if your application is refused. A full fee schedule is available on the council's website."
    },
    "resources": {
      "h2": "Useful Resources",
      "links": [
        {
          "title": "Submit Planning Application",
          "url": "https://www.manchester.gov.uk/planning/apply"
        },
        {
          "title": "Local Plan",
          "url": ""
        },
        {
          "title": "Planning Committee",
          "url": ""
        },
        {
          "title": "Download Custom Report",
          "url": "/api/reports/custom?authority=manchester"
        }
      ]
    }
  },
  "raw_data": {
    "core_metrics": {},
    "trends": {
      "monthly": []
    },
    "top_entities": {
      "agents": [],
      "developers": []
    },
    "geographic": {
      "wards": []
    },
    "notable_applications": [],
    "comparative": {
      "regional": [],
      "national": {
        "approval_rate": 65.1,
        "avg_decision_time": 45
      }
    },
    "charts": {}
  },
  "metadata": {
    "total_words": 5241,
    "total_sections": 13,
    "total_visualizations": 8,
    "scraper_used": "Firecrawl",
    "generation_cost": 8.529180000000004,
    "meets_word_count": false
  }
}