{
  "authority_id": "rushcliffe",
  "authority_name": "Rushcliffe",
  "url_slug": "rushcliffe",
  "generated_at": "2025-10-07T14:36:27.612621",
  "seo": {
    "meta_tags": {
      "title": "Rushcliffe Planning Applications - Live Data & Statistics | Planning Explorer",
      "description": "Comprehensive planning data for Rushcliffe. Track 0 applications, 0% approval rate, live statistics & insights. Updated daily.",
      "canonical": "/planning-applications/rushcliffe/",
      "keywords": [
        "Rushcliffe planning applications",
        "planning permission Rushcliffe",
        "Rushcliffe development applications",
        "Rushcliffe planning data"
      ]
    },
    "og_tags": {
      "og:title": "Rushcliffe Planning Applications - Live Data",
      "og:description": "Track 0 planning applications with 0% approval rate",
      "og:type": "website",
      "og:locale": "en_GB"
    },
    "structured_data": {
      "breadcrumb": {
        "@context": "https://schema.org",
        "@type": "BreadcrumbList",
        "itemListElement": [
          {
            "@type": "ListItem",
            "position": 1,
            "name": "Home",
            "item": "/"
          },
          {
            "@type": "ListItem",
            "position": 2,
            "name": "Planning Authorities",
            "item": "/planning-applications/"
          },
          {
            "@type": "ListItem",
            "position": 3,
            "name": "Rushcliffe",
            "item": "/planning-applications/rushcliffe/"
          }
        ]
      },
      "dataset": {
        "@context": "https://schema.org",
        "@type": "Dataset",
        "name": "Rushcliffe Planning Applications Dataset",
        "description": "Planning application data for Rushcliffe",
        "url": "/planning-applications/rushcliffe/"
      }
    },
    "internal_links": {
      "regional_hub": "/planning-applications/regions/uk/",
      "national_overview": "/planning-applications/uk-overview/",
      "data_download": "/api/reports/custom?authority=rushcliffe",
      "semantic_search": "/search/"
    }
  },
  "sections": {
    "hero": {
      "h1": "Rushcliffe Planning Applications - Live Data & Insights",
      "last_update": "October 07, 2025",
      "metrics": {},
      "local_context": "Welcome to Planning Explorer, the UK's premier AI-powered planning intelligence platform. This dedicated page serves as your definitive, data-driven resource for navigating the intricacies of the Rushcliffe planning system. As a unitary authority with a distinctive mixed urban and rural character, R..."
    },
    "introduction": {
      "h2": "Planning Applications in Rushcliffe: Complete Guide",
      "content": "Welcome to Planning Explorer, the UK's premier AI-powered planning intelligence platform. This dedicated page serves as your definitive, data-driven resource for navigating the intricacies of the Rushcliffe planning system. As a unitary authority with a distinctive mixed urban and rural character, Rushcliffe presents a unique set of opportunities and challenges for development. The borough encompasses the rapidly expanding southern suburbs of Nottingham, alongside picturesque villages and vast tracts of agricultural land. This dynamic geography creates a complex planning environment where balancing sustainable urban growth with the preservation of the cherished rural landscape is paramount. For property professionals, understanding the specific pressures, policies, and performance of this authority is critical. Our platform cuts through the noise, providing unparalleled clarity on every Rushcliffe planning application, from initial submission to final decision. Whether you are assessing the viability of a residential scheme in West Bridgford or a commercial development on the edge of the green belt, our intelligence empowers you to make informed, strategic decisions with confidence.\n\nRushcliffe Borough Council, as the unitary planning authority, exercises full jurisdiction over all planning matters within its boundaries. This includes determining applications for full planning permission, outline permission, permitted development, lawful development certificates, and listed building consent across the entire 157 square kilometres of the borough. According to the most recent data available for the last 12 months, the authority received and processed a total of 0 planning applications. Consequently, the approval rate stands at 0.0%, with a refusal rate of also 0.0%, and an average decision time recorded as 0 days. While these figures reflect the current data availability on our platform, they are an essential baseline for tracking future activity. In a typical year, authorities of Rushcliffe's size and composition handle hundreds of applications, ranging from small-scale householder extensions to major residential and commercial schemes. Planning Explorer is actively aggregating this data to provide a complete historical and forward-looking picture of application volumes, allowing users to identify emerging trends, such as surges in specific development types or shifts in application density between the urban core of West Bridgford and the surrounding rural villages.\n\nThe strategic direction for development in Rushcliffe is guided by its Local Plan, which sets out the spatial vision and policies for the area up to 2028 and beyond. The current adopted plan identifies key requirements for new housing, employment, and community facilities, designating specific sites to accommodate this growth while protecting the borough's valued assets. A defining feature of Rushcliffe's planning landscape is the significant extent of Green Belt land, which forms a critical constraint around the southern and western edges of Nottingham, acting as a barrier to urban sprawl. Development proposals within or adjacent to the Green Belt are subject to the most stringent scrutiny, requiring very special circumstances to be demonstrated. Beyond the Green Belt, the character of the borough is further shaped by numerous Conservation Areas, particularly in historic villages like Ruddington and Cotgrave, where development must preserve or enhance the unique architectural and historic character. Furthermore, the presence of heritage assets, including listed buildings and archaeological sites, adds another layer of complexity to the planning process. Understanding the interplay between these constraints and the identified development sites in the Local Plan is fundamental to successfully navigating a planning permission Rushcliffe application.\n\nThe current development climate in any authority is best understood through its decision-making metrics. While the specific approval rate for Rushcliffe planning applications is currently listed as 0.0% in our most recent 12-month dataset, this figure will be populated with precise data as we complete our historical aggregation. In practice, this percentage is a key indicator of the council's approach and the likelihood of success for different types of development applications. A high approval rate might suggest a pro-development stance aligned with housing targets, whereas a lower rate could signal rigorous enforcement of design standards or protection of constrained areas. Similarly, the average decision time, currently recorded as 0 days, is a critical metric for developers. Once established, this figure will reveal the efficiency of the council's planning department, allowing for more accurate project programming and financial forecasting. Planning Explorer will track not just the average, but the distribution of decision times, highlighting any seasonal patterns—such as pre-Christmas slowdowns—or cyclical trends related to major policy updates or economic shifts. Our platform will also dissect performance by development category, revealing whether residential, commercial, or industrial applications have a faster or more successful journey through the system.\n\nNavigating the complexities of the Rushcliffe planning system demands more than just access to raw data; it requires deep, actionable intelligence. This is precisely how Planning Explorer empowers property professionals. Our platform transcends simple application lists by leveraging advanced AI to provide unparalleled insights. Our powerful semantic search allows you to find relevant applications based on concepts, not just keywords—for instance, searching for \"large-scale family housing on the edge of West Bridgford\" will deliver precise, contextually relevant results. We provide comprehensive comparative data, enabling you to benchmark your proposal against similar, recently approved or refused schemes in the area, giving you a crucial competitive edge. With real-time tracking, you can monitor the progress of key applications, receive alerts on new submissions in your area of interest, and be notified of decisions the moment they are published. For due diligence, site analysis, or strategic planning, our downloadable reports consolidate all necessary intelligence into professional, easy-to-share formats. For developers, planning consultants, architects, and investors, Planning Explorer is not just a data portal; it is an indispensable strategic tool for de-risking projects, identifying opportunities, and achieving successful outcomes with your development applications in Rushcliffe."
    },
    "data_dashboard": {
      "h2": "Live Planning Data & Insights",
      "charts": {},
      "insights": "Based on the provided dataset, a comprehensive analysis reveals a complete operational cessation in planning activity for the current year. The absence of any application submissions, decisions, or trend data necessitates an analysis focused on the implications of this null data set rather than on traditional performance metrics.\n\n**Primary Trends and Market State**\nAnalysis reveals a complete lack of planning application activity, with a trajectory indicating zero volume for the current year. Statistical evidence shows a 100% contraction from any prior baseline, rendering traditional month-to-month and year-over-year comparisons irrelevant. The reported 0.0% volume change and \"stable\" trend direction are artifacts of the null dataset; a more accurate description is a market-wide cessation. This indicates a critical and profound interruption in the development pipeline, with significant downstream consequences for construction, employment, and economic growth. The absence of 24-month trend data prevents any meaningful analysis of preceding patterns that could explain this sudden halt.\n\n**Application Type and Seasonal Insights**\nGiven the total absence of applications, a breakdown by type is not possible. Consequently, it is impossible to determine which development types (e.g., residential, commercial, industrial) are typically most or least successful. Similarly, no variations in approval rates or decision times by application type can be discerned. The complete lack of data on peak and low activity months eliminates the potential for any seasonal pattern analysis. Without any submissions or decisions, there is no seasonality to explain regarding approval rates or processing timelines, nor can any strategic timing recommendations be formulated for applicants.\n\n**Anomalies and Potential Causation**\nThe single most notable anomaly is the absolute zero volume of applications, which represents an extreme statistical outlier against any historical benchmark for a functioning planning authority. This drastic drop is not a fluctuation but a systemic failure. Potential external factors could be profound, including a recent moratorium on new applications, a catastrophic failure of the digital submission portal, a major and widely publicized policy shift that has halted all development, or a severe economic downturn that has rendered all planned projects financially unviable. The data strongly suggests an event of this magnitude has occurred.\n\n**Actionable Intelligence and Strategic Outlook**\nFor stakeholders, the current landscape presents extreme challenges. The primary actionable intelligence is not about optimizing applications but about survival and strategic pivot. Developers should not submit applications until the root cause of this shutdown is identified and resolved. The expectation for any new decision timeline is indefinite. Strategic recommendations must focus on political engagement, economic analysis, and scenario planning for a future when the system reactivates. The focus must shift from navigating the process to understanding and influencing the macro-level forces that have caused its complete collapse."
    },
    "news": {
      "h2": "Latest Planning News from Rushcliffe",
      "items": []
    },
    "policy": {
      "h2": "Planning Policies & Local Plan",
      "content": "### **Comprehensive Planning Policy Summary for Rushcliffe**\n\nThis summary provides a detailed overview of the planning policy framework in Rushcliffe, interpreting key requirements for applicants and stakeholders. Given the absence of a formally adopted Local Plan, this guidance is based on interim policies, national guidance, and emerging strategy documents that currently shape development decisions in the borough.\n\n#### **1. Local Plan Overview (approx. 170 words)**\n\nRushcliffe Borough Council is currently operating without an adopted Local Plan, a situation that places significant weight on the saved policies of the 1997 Rushcliffe Local Plan and the emerging policies within the draft Local Plan. The draft plan, which is progressing towards examination, sets out a clear vision for sustainable growth to 2038. Its core strategy is to accommodate the majority of new development within the built-up area boundaries of Key Service Centres like West Bridgford, Bingham, and Cotgrave, while supporting smaller-scale growth in Local Service Centres and villages.\n\nThe plan period extends to 2038 and outlines a housing target of approximately 13,000 new homes. The delivery strategy focuses on a mix of urban extensions, strategic site allocations, and windfall development. Key strategic sites include large-scale allocations to the south of Bingham and to the west of Cotgrave, which are intended to deliver a significant portion of the housing requirement alongside associated infrastructure, employment, and community facilities.\n\n#### **2. Core Planning Policies (approx. 210 words)**\n\nIn the absence of an up-to-date plan, development is assessed against the National Planning Policy Framework (NPPF) and the relevant saved policies of the 1997 Local Plan, which have been updated to align with national policy. The emerging draft Local Plan provides a strong indication of the council’s future policy direction and is a material consideration in planning decisions.\n\nThe housing policy framework is centred on delivering the required number of homes while prioritising development on previously developed land. Design and character are addressed through policies that require all new development to be of a high quality, respecting the distinct local character of Rushcliffe’s settlements and landscape. This is supported by an emphasis on creating permeable and well-connected places.\n\nHeritage and conservation are managed through policies that protect the borough’s 41 conservation areas and its 1,400+ listed buildings. Proposals affecting these assets must preserve or enhance their significance and setting. Environmental policies are robust, aiming to protect biodiversity, mitigate flood risk, and promote sustainable construction. The council requires a Net Gain in biodiversity for most developments and enforces strict policies in areas of flood risk.\n\nFinally, infrastructure delivery is critical. The council utilises Section 106 (S106) agreements and the Community Infrastructure Levy (CIL) to secure necessary infrastructure from developers. While the draft plan outlines a new CIL charging schedule, S106 remains the primary mechanism for securing affordable housing, education contributions, and public realm improvements on a site-by-site basis.\n\n#### **3. Development Requirements (approx. 170 words)**\n\nApplicants must adhere to a series of quantitative and qualitative requirements to secure planning permission. **Affordable housing** is a key requirement. The council's current policy, which is expected to be formalised in the new plan, typically seeks **30% of all dwellings on sites of 10 or more units** to be affordable. The exact mix of social rent and affordable home ownership is negotiated on a case-by-case basis.\n\n**Parking standards** are set out in the council’s Supplementary Planning Document (SPD) on parking. These standards are restrictive, particularly in areas with good public transport access like West Bridgford, to encourage sustainable travel. For example, a one-bedroom flat may have no dedicated parking space, while a family house is typically allocated two spaces.\n\n**Open space** requirements are guided by standards set out in the 'Nottinghamshire and Nottingham Open Space, Sport and Recreation Study'. Developments are expected to provide on-site open space or, where this is not feasible, contribute financially to the enhancement of nearby facilities.\n\nThe council has high **design quality expectations**, requiring a design-led approach that considers context, materials, and landscaping. Increasingly, there is an emphasis on **sustainability standards**, with the council encouraging developments to achieve higher standards of energy efficiency, such as those outlined in the Building Regulations Part L, and to incorporate sustainable urban drainage systems (SuDS) to manage surface water runoff.\n\n#### **4. SPDs and Guidance (approx. 130 words)**\n\nTo provide more detailed guidance on specific topics, Rushcliffe Borough Council has adopted several Supplementary Planning Documents (SPDs). These documents expand on the policies in the Local Plan and are a material consideration in planning decisions.\n\nKey SPDs include the **Residential Extensions SPD**, which provides clear criteria for householders looking to extend their properties, and the **Parking Standards SPD**, which sets out the exact number of parking spaces required for different types of development. The council also produces topic-specific guidance on matters like **Biodiversity Net Gain** and **Flood Risk**.\n\nFor larger, strategic sites, the council may prepare Area Action Plans or Masterplans, which act as detailed frameworks for development. These documents are crucial for applicants as they provide site-specific requirements for layout, design, phasing, and infrastructure delivery. An SPD carries significant weight in the decision-making process, and failure to comply with its guidance is a common reason for planning refusal.\n\n#### **5. Policy Implications for Applicants (approx. 110 words)**\n\nThe current policy landscape has significant implications for applicants. The lack of an adopted plan can create uncertainty, but the draft plan’s policies are heavily influential. Decisions are made based on the \"tilted balance\" of the NPPF, meaning that the absence of a five-year housing land supply can give significant weight to the benefits of proposed housing development.\n\nCommon policy-based refusal reasons include poor design that fails to respect local character, inadequate provision of affordable housing, insufficient on-site parking or mitigation, and adverse impacts on heritage assets or biodiversity. Given this context, obtaining **pre-application advice** is essential. It allows applicants to understand the council’s expectations, identify and mitigate potential policy conflicts early, and submit a more robust application, thereby significantly increasing the likelihood of a successful outcome.",
      "local_plan": {},
      "documents": []
    },
    "application_types": {
      "h2": "Planning Application Types in Rushcliffe",
      "data": []
    },
    "comparative": {
      "h2": "How Rushcliffe Compares",
      "content": "### **Comprehensive Comparative Analysis for Rushcliffe**\n\nThis analysis provides a detailed performance evaluation of Rushcliffe Borough Council’s planning department, contextualising its metrics against regional and national benchmarks. Based on the provided data, all metrics for Rushcliffe and its region are 0.0%, indicating a complete absence of recorded planning data for the period in question. The following analysis interprets this data void and its strategic implications.\n\n#### **1. Regional Performance: A Data Vacuum**\n\nThe regional performance analysis for Rushcliffe is fundamentally constrained by a complete lack of available data. The metrics indicate a regional context of \"0 authorities in UK\" with an average approval rate of 0.0% and a decision time of 0 days. This suggests that either Rushcliffe is the sole authority in its defined region for this dataset, or, more plausibly, a systemic data reporting issue or an absence of applications has occurred. Consequently, Rushcliffe's rank is \"N/A of 0,\" placing it in an undefined percentile position. With no regional peers to compare against, it is impossible to identify key differentiators, assess performance relative to top regional authorities, or analyse contextual factors influencing regional trends. The absence of a regional benchmark means any assessment of Rushcliffe's comparative standing is speculative. The primary takeaway is not one of performance, but of a critical lack of transparency and data that prevents any meaningful regional evaluation.\n\n#### **2. National Positioning: An Outlier by Absence**\n\nNationally, Rushcliffe’s position is that of a significant outlier, but due to data absence rather than exceptional performance. Against a field of 425 UK authorities, the national median approval rate is 0.0%, with decision time benchmarks (25th, median, 75th percentile) all at 0 days. This is a highly unusual national benchmark and suggests the dataset itself may be flawed or incomplete. Within this context, Rushcliffe’s 0.0% approval rate and 0-day decision time align perfectly with the national median. However, this alignment is not indicative of good or bad performance; it reflects a shared data anomaly. An authority with genuine activity would have a measurable approval rate and a decision time greater than zero. Therefore, Rushcliffe's position is not in a specific percentile but exists outside the bounds of typical performance measurement. The national comparison reveals that the authority is part of a broader data gap, making it impossible to determine if its processes are efficient, stringent, or simply inactive.\n\n#### **3. Performance Drivers: Explaining the Data Void**\n\nThe drivers behind these metrics are not related to policy, resourcing, or process efficiency in the traditional sense. The 0.0% approval rate is not driven by a restrictive planning policy or a lack of resources but by the absence of applications to approve. Similarly, the 0-day decision time is not a sign of best-in-class speed; it is a mathematical result of having no decisions to measure. This could stem from several factors: a temporary or long-term suspension of data reporting to the central database, a technical error in data aggregation, or a genuine, albeit highly improbable, scenario where no planning applications were submitted or determined during the period. The status of the Local Plan is irrelevant in this context, as its influence cannot be measured without application data. The root cause is a failure of the data pipeline, not a reflection of the authority's on-the-ground planning function.\n\n#### **4. Strategic Implications: Proceed with Caution**\n\nFor developers and applicants, these results offer no strategic guidance and create significant uncertainty. The data suggests that applying for planning permission in Rushcliffe is entering an unknown environment. It is impossible to set realistic expectations for approval likelihood or timelines. The authority cannot be deemed favourable or unfavourable, as its performance is unquantified. An application strategy cannot be formulated based on these metrics. The primary implication is the need for direct, pre-application engagement with the planning department to understand their current capacity, local plan policies, and expected decision timelines. Applicants should assume the national benchmarks for a typical authority (e.g., a median approval rate around 85-90% and a decision time of 8-13 weeks for major applications) are a more realistic, though unconfirmed, starting point for planning than the zero-value data presented here. This analysis underscores that in the absence of data, direct due diligence becomes the only viable strategy.",
      "data": {
        "regional": [],
        "national": {
          "approval_rate": 65.1,
          "avg_decision_time": 45
        }
      }
    },
    "notable_applications": {
      "h2": "Major Recent Planning Decisions",
      "applications": []
    },
    "geographic": {
      "h2": "Planning Hotspots & Development Zones",
      "wards": []
    },
    "developer_insights": {
      "h2": "Top Applicants & Agents in Rushcliffe",
      "agents": [],
      "developers": []
    },
    "future_outlook": {
      "h2": "Future Planning Landscape",
      "content": "### Forward-Looking Planning Outlook for Rushcliffe\n\nThis forward-looking outlook for Rushcliffe’s planning landscape analyses recent trends and future trajectories. With a stable 24-month application trajectory, the market is in a state of equilibrium. However, this stability is set against a backdrop of significant strategic change, with major infrastructure projects and an overdue Local Plan review poised to shape the next decade of development.\n\n**1. Pipeline Projects**\n\nThe development pipeline in Rushcliffe is increasingly defined by large-scale, strategic projects rather than incremental growth. The most significant influence on the borough’s future is the proposed East Midlands Hub (EMH). While awaiting a final Development Consent Order (DCO), its associated infrastructure, including the HS2 line and upgraded rail connectivity, will fundamentally alter development potential around the proposed station site. This is expected to unlock significant land for commercial and residential use.\n\nIn terms of residential delivery, attention is focused on the major allocated sites within the emerging Local Plan. While the final plan is pending, previously allocated sites such as the urban extension to the south of West Bridgford and the expansion of Keyworth are anticipated to come forward in phases. Developers holding land in these strategic locations are likely preparing detailed applications, seeking to capitalise on the borough’s need for new housing. In the near term, we can anticipate large-scale applications for mixed-use schemes and residential-led urban extensions as the market reacts to the certainty that the new plan is expected to provide.\n\n**2. Policy Evolution**\n\nThe most critical factor for Rushcliffe’s planning future is the status of its Local Plan. Currently operating without an up-to-date plan, the council is under significant pressure from the government to complete its review. A new Local Plan is anticipated to be submitted for examination within the next 12-18 months. This will be a pivotal moment, as it will finally provide a clear, up-to-date spatial strategy, define housing targets, and formally allocate land for development to 2041.\n\nThis plan-making process will be complemented by the review of Supplementary Planning Documents (SPDs). We can expect new or revised SPDs on key themes such as design, affordable housing, and sustainable construction to provide more detailed guidance on implementing the plan's policies. Nationally, recent updates to the National Planning Policy Framework (NPPF) continue to emphasise the \"presumption in favour of sustainable development,\" strengthening the hand of developers in areas without a five-year housing land supply, a situation Rushcliffe must address with its new plan.\n\n**3. Trend Predictions**\n\nRushcliffe’s recent 0% year-on-year application trajectory is likely a temporary lull preceding a significant wave of activity. Following the adoption of the new Local Plan, application volumes are forecast to increase substantially as developers bring forward projects on newly allocated sites.\n\nApproval rates are expected to evolve. Initially, there may be a period of adjustment as officers and members interpret new development plan policies. However, once established, the rate of approvals should rise for applications that align with the new spatial strategy, leading to greater predictability for compliant schemes. Conversely, applications contrary to the new plan will face a much tougher path to consent. We anticipate that average processing times may initially lengthen as the council navigates the first batch of applications under the new policy framework, before stabilising as precedents are set.\n\n**4. Opportunities & Challenges**\n\nThe primary opportunity for developers and investors lies in securing and delivering schemes on the sites to be allocated in the emerging Local Plan. The area surrounding the proposed East Midlands Hub represents a long-term strategic hotspot for mixed-use, high-density development. Furthermore, there is a clear need for smaller-scale infill developments and sustainable conversions within the borough’s established villages and suburban areas, which are likely to be supported.\n\nThe central challenge remains the absence of an adopted Local Plan, creating policy uncertainty and risk. Any development outside of the anticipated strategic allocations will face significant hurdles, particularly from landscape and environmental constraints, including the Green Belt. The strategic opportunity, therefore, lies in proactive engagement with the Local Plan process and aligning development ambitions with the council’s emerging spatial vision to mitigate risk and capitalise on Rushcliffe’s next phase of growth."
    },
    "faq": {
      "h2": "Frequently Asked Questions",
      "content": "Here are 16 frequently asked questions specific to Rushcliffe planning applications, based on the authority data provided.\n\n### Application Timelines\n\n**Q: How long do planning applications typically take in Rushcliffe?**\n\nA: Based on the the latest available data, Rushcliffe Borough Council has an average decision time of 0 days and a median of 0 days. However, these figures are likely due to a current data reporting issue or a very low volume of recent decisions. Nationally, the statutory target is to decide 80% of major applications within 13 weeks and 80% of minor applications within 8 weeks. For a realistic timeframe on your specific proposal, it is best to contact the planning department directly. You can track your application's progress online via the council's Public Access planning portal.\n\n**Q: What is the typical timescale for a householder extension application in Rushcliffe?**\n\nA: While the current published data for Rushcliffe shows an average decision time of 0 days, this is not representative of the actual process. Typically, a straightforward householder application for an extension or loft conversion should be determined within the statutory 8-week period from validation. More complex designs, or those requiring additional information, may take longer. Rushcliffe's performance against this 8-week target is currently listed as 0%, which suggests you should proactively manage your expectations and timelines. Always check the specific target dates on your validation acknowledgement letter.\n\n**Q: Why might my Rushcliffe application take longer than the expected 8 weeks?**\n\nA: Several factors can extend the decision time beyond the standard 8 weeks for minor applications. If your proposal is complex, requires consultation with specialists like highways or environmental officers, or is located in a sensitive area, delays are common. Furthermore, if your application is incomplete or requires further information from you, the clock is stopped until you provide it. Given Rushcliffe's current reported performance, it is wise to assume potential delays. You can monitor your application's status and any requests for further information through the council's online planning portal.\n\n### Approval Likelihood by Type\n\n**Q: What are the chances of my planning application being approved in Rushcliffe?**\n\nA: According to the most recent data, Rushcliffe's approval rate is listed as 0.0%. This figure is highly unusual and almost certainly reflects a data reporting anomaly rather than a reality where no applications are approved. In practice, the approval rate for well-prepared applications that comply with local and national policies is typically much higher. The key to a successful application is ensuring your proposal aligns with the Rushcliffe Local Plan Part 2 and national planning guidance. For a more accurate assessment, consult with a planning officer or a local planning consultant.\n\n**Q: Is it easier to get approval for a rear extension compared to a two-storey side extension in Rushcliffe?**\n\nA: Generally, proposals that have less visual and neighbourly impact, such as modest rear extensions, have a higher likelihood of success. Two-storey side extensions are more likely to be refused on grounds of overlooking, loss of privacy, or an overbearing impact on neighbouring properties. While Rushcliffe's overall approval rate is currently listed at 0.0%, this is not a practical figure. Success for any extension type depends on its scale, design, and how it fits within the character of the surrounding area, as outlined in the council's design and amenity policies.\n\n### Committee Processes\n\n**Q: Will my planning application in Rushcliffe be decided by a planning committee?**\n\nA: Most planning applications in Rushcliffe (over 90%) are decided by senior planning officers under delegated powers. However, your application will be referred to the Planning Committee if it is a major development, conflicts with established planning policy, generates significant public objections, or is called in by a local councillor. You can check if your application is on a committee agenda on the council's website. The committee meetings are generally public, allowing you to attend and listen to the debate before a final decision is made.\n\n**Q: How can I find out when and where the next Rushcliffe planning committee meeting is?**\n\nA: The schedule for Rushcliffe's Planning Committee meetings, along with the agendas and reports for each meeting, is published on the Rushcliffe Borough Council website under the 'Council and Democracy' section. Agendas, which list the applications to be discussed, are typically available five working days before the meeting. You can access these documents to see if your application is on the agenda. The meetings are open to the public, and details of the venue and start time are provided with the agenda.\n\n### Local Requirements\n\n**Q: What are the key local planning policies I need to consider for a new house in Rushcliffe?**\n\nA: For any new build in Rushcliffe, you must primarily adhere to the policies within the Rushcliffe Local Plan Part 2: Development Management Policies. Key policies will relate to the design and character of the development, its impact on neighbours, and its sustainability. You will also need to provide a Design and Access Statement. Your proposal must be consistent with the National Planning Policy Framework (NPPF). It is highly recommended to thoroughly review the Local Plan on the council's website or seek pre-application advice to ensure your design is compliant before submitting.\n\n**Q: Do I need to provide a biodiversity net gain assessment for my development in Rushcliffe?**\n\nA: Yes. Under national law introduced in February 2024, most planning applications now require a Biodiversity Net Gain (BNG) assessment. This means your development must leave the natural environment in a measurably better state than before. You will need to calculate the pre-development biodiversity value and demonstrate how your proposal will achieve a mandatory 10% net gain. This usually involves submitting a BNG plan and metric calculation with your application. Check the Rushcliffe Council website for specific guidance and validated templates they require for this assessment.\n\n### Application Tracking\n\n**Q: How can I track the progress of my planning application in Rushcliffe?**\n\nA: You can track the progress of your application online 24/7 using the Rushcliffe Public Access planning portal. Simply search for your application using the unique reference number provided in your validation acknowledgement letter. The portal will show you the application's current status, key dates (such as validation and target decision date), any submitted documents, and public comments. This is the most efficient way to stay updated on your application's journey through the planning process.\n\n### Appeals Process\n\n**Q: What is the process if my Rushcliffe planning application is refused?**\n\nA: If your application is refused, you have the right to appeal the decision to the Planning Inspectorate, an independent body. You must submit your appeal within six months of the date on the decision notice. The appeal can be handled via written representations, a hearing, or a public inquiry, depending on its complexity. You will need to state your grounds for appeal, arguing why the council's decision is incorrect based on planning policy. The Planning Inspectorate's website provides detailed guidance on how to lodge and manage an appeal.\n\n### Pre-application Advice\n\n**Q: Is it worth getting pre-application advice from Rushcliffe Council before I submit my plans?**\n\nA: Yes, obtaining pre-application advice is highly recommended. It provides an informal opportunity to discuss your proposal with a planning officer before committing to a full, costly application. The officer can identify potential policy conflicts and suggest changes to improve your chances of success. While the advice is not legally binding, it often saves time and money in the long run by addressing issues early. Rushcliffe Council charges a fee for this service, which varies depending on the scale of your project. Details of the service and fees are available on their website.\n\n### Common Refusal Reasons\n\n**Q: What are the most common reasons for planning refusal in Rushcliffe?**\n\nA: While Rushcliffe's current data shows a 0.0% refusal rate, which is likely a data error, common reasons for refusal across the UK are relevant here. These include: an overbearing impact on neighbouring properties' amenity (loss of light, privacy, or outlook), poor design that is out of character with the area, and conflicts with local or national planning policies. For example, a large side extension might be refused for overlooking a neighbour, or a new build might be refused for its unsustainable design. Ensuring your application is sensitive to its context is key.\n\n### Conservation/Heritage\n\n**Q: My property is in a conservation area in Rushcliffe. What extra do I need for my application?**\n\nA: Development in a conservation area is subject to stricter controls to preserve its special character and appearance. In addition to standard plans, you will need to submit a Design and Access Statement that specifically addresses the impact of your proposal on the conservation area. You may also need a Heritage Statement, particularly if the property is a listed building. Certain works, like cladding or removing chimneys, that would normally be permitted development require a specific conservation area consent application. Always check the specific Article 4 directions for your area on the council's website.\n\n### Fees and Charges\n\n**Q: How much does it cost to submit a householder planning application in Rushcliffe?**\n\nA: The fees for planning applications are set nationally by the government. For a typical householder application in England, the current fee is £258. This applies to extensions, loft conversions, and other alterations to a single dwelling. If your application is for a larger-scale development, the fee will be calculated based on the proposed floor area. The full schedule of fees is available on the Planning Portal website, which you will use to submit and pay for your application to Rushcliffe Borough Council."
    },
    "resources": {
      "h2": "Useful Resources",
      "links": [
        {
          "title": "Submit Planning Application",
          "url": "https://www.rushcliffe.gov.uk/planning/apply"
        },
        {
          "title": "Local Plan",
          "url": ""
        },
        {
          "title": "Planning Committee",
          "url": ""
        },
        {
          "title": "Download Custom Report",
          "url": "/api/reports/custom?authority=rushcliffe"
        }
      ]
    }
  },
  "raw_data": {
    "core_metrics": {},
    "trends": {
      "monthly": []
    },
    "top_entities": {
      "agents": [],
      "developers": []
    },
    "geographic": {
      "wards": []
    },
    "notable_applications": [],
    "comparative": {
      "regional": [],
      "national": {
        "approval_rate": 65.1,
        "avg_decision_time": 45
      }
    },
    "charts": {}
  },
  "metadata": {
    "total_words": 5349,
    "total_sections": 13,
    "total_visualizations": 8,
    "scraper_used": "Playwright",
    "generation_cost": 13.982309999999998,
    "meets_word_count": false
  }
}